pycountsrmb2024/__init__.py
pycountsrmb2024/plotting.py
pycountsrmb2024/pycountsrmb2024.py
pycountsrmb2024-0.1.0.dist-info/LICENSE
pycountsrmb2024-0.1.0.dist-info/METADATA
pycountsrmb2024-0.1.0.dist-info/WHEEL
pycountsrmb2024-0.1.0.dist-info/RECORD
