Metadata-Version: 2.1
Name: pycountsrmb2024
Version: 0.1.0
Summary: Calculate word counts in a text file!
License: MIT
Author: Rachel Bouwer
Requires-Python: >=3.9
Classifier: License :: OSI Approved :: MIT License
Classifier: Programming Language :: Python :: 3
Classifier: Programming Language :: Python :: 3.9
Classifier: Programming Language :: Python :: 3.10
Classifier: Programming Language :: Python :: 3.11
Classifier: Programming Language :: Python :: 3.12
Requires-Dist: matplotlib (>=3.8.2)
